scotty/__init__.py
scotty/_version.py
scotty/analysis.py
scotty/beam_me_up.py
scotty/check_ModeConversion.py
scotty/check_input.py
scotty/check_output.py
scotty/compare_plot.py
scotty/derivatives.py
scotty/fun_evolution.py
scotty/fun_general.py
scotty/geometry.py
scotty/hamiltonian.py
scotty/hornpy.py
scotty/init_bruv.py
scotty/launch.py
scotty/lensalot.py
scotty/outplot.py
scotty/plotting.py
scotty/profile_fit.py
scotty/ray_solver.py
scotty/torbeam.py
scotty/typing.py
scotty_beam_tracing-3.0.3.dist-info/licenses/LICENSE.md
scotty_beam_tracing-3.0.3.dist-info/METADATA
scotty_beam_tracing-3.0.3.dist-info/WHEEL
scotty_beam_tracing-3.0.3.dist-info/top_level.txt
scotty_beam_tracing-3.0.3.dist-info/RECORD
