Metadata-Version: 2.4
Name: scotty-beam-tracing
Version: 3.0.3
Summary: Beam tracing for tokamak DBS diagnostics
Author: Valerian Hall-Chen
Project-URL: project, https://github.com/valerian-chen/Scotty
Requires-Python: >=3.10
License-File: LICENSE.md
Requires-Dist: numpy>=2.0
Requires-Dist: scipy~=1.7
Requires-Dist: matplotlib~=3.3
Requires-Dist: freeqdsk>=0.1.0
Requires-Dist: xarray>=2024.10.0
Requires-Dist: h5netcdf
Provides-Extra: tests
Requires-Dist: pytest; extra == "tests"
Provides-Extra: docs
Requires-Dist: sphinx>=5.3; extra == "docs"
Requires-Dist: sphinx-book-theme>=1.1.0; extra == "docs"
Dynamic: license-file
